cguard/__init__.py
cguard/access_manager/__init__.py
cguard/access_manager/access_manager.py
cguard/access_manager/cased_guard.py
cguard/access_manager/local_guard.py
cguard/access_manager/test_guard.py
cguard/core/__init__.py
cguard/core/approval.py
cguard/core/client.py
cguard/http/__init__.py
cguard/http/httpclient.py
cguard/publisher/__init__.py
cguard/publisher/publisher.py
cguard/publisher/trails_publisher.py
cguard/requestor/__init__.py
cguard/requestor/guard_requestor.py
cguard/requestor/httpclient.py
cguard/test/__init__.py
cguard/test/test_access_manager.py
cguard/test/test_access_manger.py
cguard/test/test_approval.py
cguard/test/test_httpclient.py
cguard/test/test_requestor.py
cguard/test/test_util.py
cguard/test/util.py
cguard/util/__init__.py
cguard-0.1.0.data/scripts/cased
cguard-0.1.0.data/scripts/cased-init
cguard-0.1.0.dist-info/METADATA
cguard-0.1.0.dist-info/WHEEL
cguard-0.1.0.dist-info/top_level.txt
cguard-0.1.0.dist-info/RECORD
